README.rst
setup.cfg
setup.py
migrations4neo/__init__.py
migrations4neo/main.py
migrations4neo/template.py
migrations4neo/utils.py
migrations4neo.egg-info/PKG-INFO
migrations4neo.egg-info/SOURCES.txt
migrations4neo.egg-info/dependency_links.txt
migrations4neo.egg-info/entry_points.txt
migrations4neo.egg-info/requires.txt
migrations4neo.egg-info/top_level.txt