Metadata-Version: 1.1
Name: migrations4neo
Version: 1.0.1
Summary: Easy neo4j migrations
Home-page: https://github.com/turkus/migrations4neo
Author: turkus
Author-email: wojciechrola@wp.pl
License: UNKNOWN
Download-URL: https://github.com/turkus/migrations4neo/tarball/1.0.1
Keywords: neo4j,migrations
Platform: UNKNOWN
Classifier: Intended Audience :: Developers
Classifier: Operating System :: OS Independent
Classifier: Programming Language :: Python
Classifier: Programming Language :: Python :: 2
Classifier: Programming Language :: Python :: 2.7
Classifier: Programming Language :: Python :: 3
Classifier: Programming Language :: Python :: 3.2
Classifier: Programming Language :: Python :: 3.3
Classifier: Programming Language :: Python :: 3.4
Classifier: Programming Language :: Python :: 3.5
